scraper_hj3415/__init__.py
scraper_hj3415/cli.py
scraper_hj3415/krx300/__init__.py
scraper_hj3415/krx300/krx.db
scraper_hj3415/krx300/krx300.py
scraper_hj3415/krx300/temp/20250110.xls
scraper_hj3415/miscraper/__init__.py
scraper_hj3415/miscraper/run.py
scraper_hj3415/miscraper/scrapy.cfg
scraper_hj3415/miscraper/mis/__init__.py
scraper_hj3415/miscraper/mis/items.py
scraper_hj3415/miscraper/mis/middlewares.py
scraper_hj3415/miscraper/mis/pipelines.py
scraper_hj3415/miscraper/mis/spiders/__init__.py
scraper_hj3415/miscraper/mis/spiders/mi.py
scraper_hj3415/miscraper/mis/spiders/mihistory.py
scraper_hj3415/nfscraper/__init__.py
scraper_hj3415/nfscraper/common.py
scraper_hj3415/nfscraper/run.py
scraper_hj3415/nfscraper/scrapy.cfg
scraper_hj3415/nfscraper/nfs/__init__.py
scraper_hj3415/nfscraper/nfs/items.py
scraper_hj3415/nfscraper/nfs/middlewares.py
scraper_hj3415/nfscraper/nfs/pipelines.py
scraper_hj3415/nfscraper/nfs/spiders/__init__.py
scraper_hj3415/nfscraper/nfs/spiders/c101.py
scraper_hj3415/nfscraper/nfs/spiders/c103.py
scraper_hj3415/nfscraper/nfs/spiders/c104.py
scraper_hj3415/nfscraper/nfs/spiders/c106.py
scraper_hj3415/nfscraper/nfs/spiders/c108.py
scraper_hj3415-4.8.3.dist-info/entry_points.txt
scraper_hj3415-4.8.3.dist-info/WHEEL
scraper_hj3415-4.8.3.dist-info/METADATA
scraper_hj3415-4.8.3.dist-info/RECORD
