Metadata-Version: 2.3
Name: scraper_hj3415
Version: 4.8.3
Summary: Gathering the stock data
Author-email: Hyungjin Kim <hj3415@gmail.com>
Classifier: License :: OSI Approved :: MIT License
Requires-Dist: scrapy>=2.12.0
Requires-Dist: db-hj3415>=4.6.2
Requires-Dist: pandas>=2.2.2
Requires-Dist: webdriver-hj3415>=2.0.0
Requires-Dist: utils_hj3415>=3.2.0
Requires-Dist: xlrd==2.0.1
Project-URL: Home, https://www.hyungjin.kr
